codextend/__init__.py
codextend-1.1.0.11.dist-info/LICENSE
codextend-1.1.0.11.dist-info/METADATA
codextend-1.1.0.11.dist-info/WHEEL
codextend-1.1.0.11.dist-info/entry_points.txt
codextend-1.1.0.11.dist-info/top_level.txt
codextend-1.1.0.11.dist-info/RECORD
