Metadata-Version: 2.2
Name: codextend
Version: 1.1.0.11
Summary: A Python module The encoding and the encoding format can be converted.
Author: caaat
Author-email: caaat <caaatstar@qq.com>
Keywords: code,extension,utility
Classifier: Development Status :: 3 - Alpha
Classifier: Intended Audience :: Developers
Classifier: License :: OSI Approved :: MIT License
Classifier: Programming Language :: Python :: 3
Classifier: Programming Language :: Python :: 3.6
Classifier: Programming Language :: Python :: 3.7
Classifier: Programming Language :: Python :: 3.8
Classifier: Programming Language :: Python :: 3.9
Requires-Python: >=3.6
License-File: LICENSE
Requires-Dist: chardet
Requires-Dist: cryptography
Dynamic: author
Dynamic: requires-python
